pretix_sortir/__init__.py
pretix_sortir/api.py
pretix_sortir/apps.py
pretix_sortir/fields.py
pretix_sortir/forms.py
pretix_sortir/logging_filters.py
pretix_sortir/models.py
pretix_sortir/navigation.py
pretix_sortir/signals.py
pretix_sortir/urls.py
pretix_sortir/views.py
pretix_sortir/migrations/0001_initial.py
pretix_sortir/migrations/0002_add_api_url_fields.py
pretix_sortir/migrations/0003_rename_pretix_sort_event_i_5b5c5f_idx_pretix_sort_event_i_9db569_idx_and_more.py
pretix_sortir/migrations/0004_set_api_enabled_default_true.py
pretix_sortir/migrations/0005_set_event_enabled_default_true.py
pretix_sortir/migrations/0006_add_api_url_fields.py
pretix_sortir/migrations/0007_encrypt_api_token.py
pretix_sortir/migrations/0008_add_unique_card_constraint.py
pretix_sortir/migrations/0009_add_audit_log.py
pretix_sortir/migrations/0010_nullable_user_agent.py
pretix_sortir/migrations/0011_add_retention_fields.py
pretix_sortir/migrations/0012_add_session_id.py
pretix_sortir/migrations/0013_simplify_api_url.py
pretix_sortir/migrations/__init__.py
pretix_sortir/static/pretix_sortir/sortir.css
pretix_sortir/static/pretix_sortir/sortir.js
pretix_sortir/templates/pretix_sortir/checkout_sortir.html
pretix_sortir/templates/pretix_sortir/event_settings.html
pretix_sortir/templates/pretix_sortir/item_config.html
pretix_sortir/templates/pretix_sortir/items_list.html
pretix_sortir/templates/pretix_sortir/organizer_settings.html
pretix_sortir/templates/pretix_sortir/usage_list.html
pretix_sortir-1.0.1.dist-info/licenses/LICENSE
pretix_sortir-1.0.1.dist-info/METADATA
pretix_sortir-1.0.1.dist-info/WHEEL
pretix_sortir-1.0.1.dist-info/entry_points.txt
pretix_sortir-1.0.1.dist-info/top_level.txt
pretix_sortir-1.0.1.dist-info/RECORD
