Metadata-Version: 2.4
Name: pretix-sortir
Version: 1.0.1
Summary: Pretix plugin for Sortir! reduced fare integration
Home-page: https://github.com/valentin-gosselin/pretix-sortir
Author: Pretix Sortir Plugin Contributors
License: MIT
Project-URL: Homepage, https://github.com/valentin-gosselin/pretix-sortir
Project-URL: Documentation, https://github.com/valentin-gosselin/pretix-sortir/blob/main/README.md
Project-URL: Repository, https://github.com/valentin-gosselin/pretix-sortir
Project-URL: Issues, https://github.com/valentin-gosselin/pretix-sortir/issues
Keywords: pretix,plugin,sortir,apras,tickets,reduced-fare
Classifier: Development Status :: 4 - Beta
Classifier: Environment :: Plugins
Classifier: Framework :: Django
Classifier: Framework :: Django :: 3.2
Classifier: Framework :: Django :: 4.0
Classifier: Framework :: Django :: 4.1
Classifier: Framework :: Django :: 4.2
Classifier: Intended Audience :: Developers
Classifier: Intended Audience :: Other Audience
Classifier: License :: OSI Approved :: MIT License
Classifier: Programming Language :: Python :: 3
Classifier: Programming Language :: Python :: 3.8
Classifier: Programming Language :: Python :: 3.9
Classifier: Programming Language :: Python :: 3.10
Classifier: Programming Language :: Python :: 3.11
Classifier: Topic :: Internet :: WWW/HTTP :: Dynamic Content
Requires-Python: >=3.8
License-File: LICENSE
Dynamic: home-page
Dynamic: license-file
Dynamic: requires-python
